<annotation>
	<folder></folder>
	<filename>Image-from-iOS--3-_jpg.rf.389e9fb06320281c4af3898e2948f469.jpg</filename>
	<path>Image-from-iOS--3-_jpg.rf.389e9fb06320281c4af3898e2948f469.jpg</path>
	<source>
		<database>roboflow.ai</database>
	</source>
	<size>
		<width>416</width>
		<height>416</height>
		<depth>3</depth>
	</size>
	<segmented>0</segmented>
	<object>
		<name>dark logo</name>
		<pose>Unspecified</pose>
		<truncated>0</truncated>
		<difficult>0</difficult>
		<occluded>0</occluded>
		<bndbox>
			<xmin>164</xmin>
			<xmax>251</xmax>
			<ymin>113</ymin>
			<ymax>154</ymax>
		</bndbox>
	</object>
</annotation>
